fantasycrypt/__init__.py
fantasycrypt/crypt.py
fantasycrypt-0.0.1.dist-info/METADATA
fantasycrypt-0.0.1.dist-info/WHEEL
fantasycrypt-0.0.1.dist-info/licenses/LICENSE
fantasycrypt-0.0.1.dist-info/RECORD
