Metadata-Version: 2.1
Name: fantasycrypt
Version: 0.0.1
Summary: FantasyCrypt Package for the AI Deceptive Content Paper
Project-URL: Homepage, https://github.com/pypa/sampleproject
Project-URL: Bug Tracker, https://github.com/pypa/sampleproject/issues
Author-email: Arjun S <0xarjun@gmail.com>
License-File: LICENSE
Classifier: License :: OSI Approved :: MIT License
Classifier: Operating System :: OS Independent
Classifier: Programming Language :: Python :: 3
Requires-Python: >=3.7
